[
    {
        "id": "futx3",
        "name": "Fut x3",
        "category": "futsal",
        "description": "Campo de fútbol para partidos 3v3",
        "author": "Bazinga from HaxMaps",
        "content": {
            "name": "Futsal x3 by Bazinga from HaxMaps",
            "width": 620,
            "height": 270,
            "spawnDistance": 350,
            "bg": {
                "type": "hockey",
                "width": 550,
                "height": 240,
                "kickOffRadius": 80,
                "cornerRadius": 0
            },
            "vertexes": [
                {"x": 550, "y": 240, "trait": "ballArea"},
                {"x": 550, "y": -240, "trait": "ballArea"},
                {"x": 0, "y": 270, "trait": "kickOffBarrier"},
                {"x": 0, "y": 80, "bCoef": 0.15, "trait": "kickOffBarrier", "color": "F8F8F8", "vis": true, "curve": 180},
                {"x": 0, "y": -80, "bCoef": 0.15, "trait": "kickOffBarrier", "color": "F8F8F8", "vis": true, "curve": 180},
                {"x": 0, "y": -270, "trait": "kickOffBarrier"}
            ],
            "goals": [
                {"team": "red", "p0": [-454.53, -5.46], "p1": [-425.15, -5.46], "cMask": ["wall"]},
                {"team": "red", "p0": [445.53, -3.46], "p1": [416.15, -3.46], "cMask": ["wall"]}
            ],
            "playerPhysics": {
                "gravity": [0, 0.2],
                "radius": 20,
                "bCoef": 1.2,
                "invMass": 0.7,
                "kickStrength": 10,
                "acceleration": 0.12,
                "damping": 0.97
            },
            "ballPhysics": {
                "gravity": [0, 0.2],
                "color": "e37f1e",
                "bCoef": 1,
                "invMass": 1,
                "damping": 0.98,
                "cMask": ["all"],
                "cGroup": ["ball"],
                "radius": 14
            }
        }
    },
    {
        "id": "ahabig",
        "name": "AHA Big v2.1",
        "category": "futsal",
        "description": "Versión grande del mapa AHA",
        "author": "AHA",
        "content": {
            "name": "AHA Big v2.1",
            "width": 600,
            "height": 270,
            "spawnDistance": 350,
            "bg": {
                "type": "grass",
                "width": 550,
                "height": 240,
                "kickOffRadius": 80,
                "cornerRadius": 0
            },
            "vertexes": [
                {"x": -550, "y": 240, "cMask": ["ball"]},
                {"x": -550, "y": 80, "cMask": ["ball"]},
                {"x": -550, "y": -80, "cMask": ["ball"]},
                {"x": -550, "y": -240, "cMask": ["ball"]},
                {"x": 550, "y": 240, "cMask": ["ball"]},
                {"x": 550, "y": 80, "cMask": ["ball"]},
                {"x": 550, "y": -80, "cMask": ["ball"]},
                {"x": 550, "y": -240, "cMask": ["ball"]}
            ],
            "goals": [
                {"p0": [-550, 80], "p1": [-550, -80], "team": "red"},
                {"p0": [550, 80], "p1": [550, -80], "team": "blue"}
            ],
            "playerPhysics": {
                "bCoef": 0.5,
                "invMass": 0.5,
                "damping": 0.96,
                "acceleration": 0.1,
                "kickingAcceleration": 0.07,
                "kickingDamping": 0.96,
                "kickStrength": 5
            },
            "ballPhysics": {
                "radius": 6.25,
                "bCoef": 0.4,
                "invMass": 1.5,
                "damping": 0.99,
                "color": "FFFFFF"
            }
        }
    }
]
